Workbook

Sheet Madurez
A1: Encuesta de madurez digital - Dulxelitos
A2: Respondida por el equipo consultor con la evidencia relevada, no por autoevaluación de la empresa. Para recalcular, cambiar solo la columna Respuesta (celdas amarillas): el puntaje y los resultados se actualizan solos.
A4: Dimensión | B4: Pregunta | C4: Respuesta | D4: Puntaje | E4: En qué nos basamos
A5: Liderazgo y Cultura Digital | B5: ¿Existe una visión digital clara comunicada por los líderes? | C5: A | D5: =IFERROR(INDEX(Resultado!$I$5:$I$9,MATCH(C5,Resultado!$H$5:$H$9,0)),"") | E5: No hay ninguna iniciativa de cambio marcada
A6: Liderazgo y Cultura Digital | B6: ¿Los líderes promueven activamente la transformación digital? | C6: A | D6: =IFERROR(INDEX(Resultado!$I$5:$I$9,MATCH(C6,Resultado!$H$5:$H$9,0)),"") | E6: Sin plan ni responsable asignado
A7: Liderazgo y Cultura Digital | B7: ¿La cultura organizacional apoya la innovación tecnológica? | C7: B | D7: =IFERROR(INDEX(Resultado!$I$5:$I$9,MATCH(C7,Resultado!$H$5:$H$9,0)),"") | E7: Aprovechan oportunidades de producto nuevo cuando aparecen
A8: Liderazgo y Cultura Digital | B8: ¿Se fomenta la experimentación y el aprendizaje continuo? | C8: B | D8: =IFERROR(INDEX(Resultado!$I$5:$I$9,MATCH(C8,Resultado!$H$5:$H$9,0)),"") | E8: Hay ganas de capacitarse, pero no hay programa
A9: Estrategia y Modelo de Negocio | B9: ¿La estrategia digital está integrada en la general? | C9: A | D9: =IFERROR(INDEX(Resultado!$I$5:$I$9,MATCH(C9,Resultado!$H$5:$H$9,0)),"") | E9: No hay estrategia digital formulada
A10: Estrategia y Modelo de Negocio | B10: ¿Se exploran nuevos modelos de negocio habilitados por tecnología? | C10: B | D10: =IFERROR(INDEX(Resultado!$I$5:$I$9,MATCH(C10,Resultado!$H$5:$H$9,0)),"") | E10: Construyeron la tienda online en 2020 y no la activaron
A11: Estrategia y Modelo de Negocio | B11: ¿Existen indicadores de éxito digital claramente definidos? | C11: A | D11: =IFERROR(INDEX(Resultado!$I$5:$I$9,MATCH(C11,Resultado!$H$5:$H$9,0)),"") | E11: No hay indicadores de éxito digital definidos
A12: Estrategia y Modelo de Negocio | B12: ¿La empresa revisa periódicamente su estrategia digital? | C12: A | D12: =IFERROR(INDEX(Resultado!$I$5:$I$9,MATCH(C12,Resultado!$H$5:$H$9,0)),"") | E12: No hay revisión periódica
A13: Tecnología y Datos | B13: ¿Cuenta con infraestructura tecnológica actualizada? | C13: B | D13: =IFERROR(INDEX(Resultado!$I$5:$I$9,MATCH(C13,Resultado!$H$5:$H$9,0)),"") | E13: Discovery (BAS), desactualizado y con errores
A14: Tecnología y Datos | B14: ¿Existen sistemas integrados (ERP, CRM)? | C14: A | D14: =IFERROR(INDEX(Resultado!$I$5:$I$9,MATCH(C14,Resultado!$H$5:$H$9,0)),"") | E14: El sistema no se integra con nada y no hay CRM
A15: Tecnología y Datos | B15: ¿Qué nivel de automatización tienen los procesos clave? | C15: C | D15: =IFERROR(INDEX(Resultado!$I$5:$I$9,MATCH(C15,Resultado!$H$5:$H$9,0)),"") | E15: Facturación, stock y cuentas corrientes en el sistema; costeo y precios a mano
A16: Tecnología y Datos | B16: ¿Se recopilan y analizan datos para la toma de decisiones? | C16: C | D16: =IFERROR(INDEX(Resultado!$I$5:$I$9,MATCH(C16,Resultado!$H$5:$H$9,0)),"") | E16: Hacen estadísticas mensuales, sin tablero ni indicadores gerenciales integrados
... A32: Gobierno | B32: ¿Se revisan riesgos de continuidad (proveedor único, backup, sucesión)? | C32: B | D32: =IFERROR(INDEX(Resultado!$I$5:$I$9,MATCH(C32,Resultado!$H$5:$H$9,0)),"") | E32: Hay backup de planillas y segunda generación, pero el proveedor único de film no se gestiona como riesgo
C33: TOTAL | D33: =SUM(D5:D32)

Sheet Resultado
A1: Resultado por dimensión
A3: Dimensión | B3: Puntos | C3: Preguntas | D3: Promedio | E3: Nivel | H3: Escala de respuesta | K3: Bandas de nivel
A4: Liderazgo y Cultura Digital | B4: =SUMIF(Madurez!$A$5:$A$32,$A4,Madurez!$D$5:$D$32) | C4: =COUNTIF(Madurez!$A$5:$A$32,$A4) | D4: =IFERROR(B4/C4,"") | E4: =IFERROR(INDEX($L$5:$L$9,MATCH(D4,$K$5:$K$9,1)),"")
A5: Estrategia y Modelo de Negocio | B5: =SUMIF(Madurez!$A$5:$A$32,$A5,Madurez!$D$5:$D$32) | C5: =COUNTIF(Madurez!$A$5:$A$32,$A5) | D5: =IFERROR(B5/C5,"") | E5: =IFERROR(INDEX($L$5:$L$9,MATCH(D5,$K$5:$K$9,1)),"") | H5: A | I5: 1 | J5: No se aplica / no implementado | K5: 0 | L5: Inicial
A6: Tecnología y Datos | B6: =SUMIF(Madurez!$A$5:$A$32,$A6,Madurez!$D$5:$D$32) | C6: =COUNTIF(Madurez!$A$5:$A$32,$A6) | D6: =IFERROR(B6/C6,"") | E6: =IFERROR(INDEX($L$5:$L$9,MATCH(D6,$K$5:$K$9,1)),"") | H6: B | I6: 2 | J6: Parcial o informal | K6: 2 | L6: Básico
A7: Procesos y Operaciones | B7: =SUMIF(Madurez!$A$5:$A$32,$A7,Madurez!$D$5:$D$32) | C7: =COUNTIF(Madurez!$A$5:$A$32,$A7) | D7: =IFERROR(B7/C7,"") | E7: =IFERROR(INDEX($L$5:$L$9,MATCH(D7,$K$5:$K$9,1)),"") | H7: C | I7: 3 | J7: Básico o reactivo | K7: 3 | L7: Intermedio
A8: Personas y Habilidades | B8: =SUMIF(Madurez!$A$5:$A$32,$A8,Madurez!$D$5:$D$32) | C8: =COUNTIF(Madurez!$A$5:$A$32,$A8) | D8: =IFERROR(B8/C8,"") | E8: =IFERROR(INDEX($L$5:$L$9,MATCH(D8,$K$5:$K$9,1)),"") | H8: D | I8: 4 | J8: Estandarizado y documentado | K8: 4 | L8: Avanzado
A9: Clientes y Canales | B9: =SUMIF(Madurez!$A$5:$A$32,$A9,Madurez!$D$5:$D$32) | C9: =COUNTIF(Madurez!$A$5:$A$32,$A9) | D9: =IFERROR(B9/C9,"") | E9: =IFERROR(INDEX($L$5:$L$9,MATCH(D9,$K$5:$K$9,1)),"") | H9: E | I9: 5 | J9: Optimizado o integrado | K9: 4.6 | L9: Transformacional
A10: Gobierno | B10: =SUMIF(Madurez!$A$5:$A$32,$A10,Madurez!$D$5:$D$32) | C10: =COUNTIF(Madurez!$A$5:$A$32,$A10) | D10: =IFERROR(B10/C10,"") | E10: =IFERROR(INDEX($L$5:$L$9,MATCH(D10,$K$5:$K$9,1)),"")
A11: GLOBAL | B11: =SUM(B4:B10) | C11: =SUM(C4:C10) | D11: =IFERROR(B11/C11,"") | E11: =IFERROR(INDEX($L$5:$L$9,MATCH(D11,$K$5:$K$9,1)),"") | K11: Cada banda es el piso del nivel: un promedio de 1.79 cae en Inicial.

Sheet FODA
A1: FODA y FODA cruzado - Dulxelitos
A3: FORTALEZAS
A4: 1 | B4: Red de 57 distribuidores en 7 provincias, armada en 53 años
A5: 2 | B5: Logística propia más tercerizada, que ellos mismos reconocen como diferencial
A6: 3 | B6: Marca con 53 años y presencia en góndola de supermercado
A7: 4 | B7: Habilitaciones RNE y RNPA vigentes
A8: 5 | B8: Segunda generación trabajando: el día a día está cubierto
A9: 6 | B9: Los distribuidores están conformes: los eligen por compromiso y precio
A10: 7 | B10: Demanda pareja todo el año, sin exposición a plazos de una cadena grande
A12: DEBILIDADES
A13: 1 | B13: El costeo por producto está mal y no está sistematizado
A14: 2 | B14: La planta está saturada y lo tapan con horas extras, sin plan de ampliar
A15: 3 | B15: No miden nada ni tienen reuniones de dirección
A16: 4 | B16: El sistema de gestión está viejo, con errores y sin integración
A17: 5 | B17: Un solo proveedor de film impreso
A18: 6 | B18: Sin CRM ni registro útil de la cartera; no saben cuánto factura cada cliente
A19: 7 | B19: Para saber si hay stock, el distribuidor tiene que llamar o ir al depósito
A20: 8 | B20: Nadie se capacitó en nada digital en los últimos dos años
A22: OPORTUNIDADES
A23: 1 | B23: La tienda online ya está construida y con catálogo cargado, solo que apagada
A24: 2 | B24: El equipo tiene ganas de capacitarse
A25: 3 | B25: Aiello funciona como modelo repetible con otras cadenas regionales
A26: 4 | B26: La línea de fraccionamiento permite crecer sin ampliar la planta
A27: 5 | B27: La competencia que enfrentan es regional, sin presión de las marcas grandes
A29: AMENAZAS
A30: 1 | B30: Inflación de insumos sobre un modelo que compite por precio
A31: 2 | B31: Que falle el proveedor único de film
A32: 3 | B32: Planta saturada: si la demanda salta, no hay con qué responder
A33: 4 | B33: Perder clientes sin enterarse, por falta de datos de la cartera
A34: 5 | B34: Que un competidor de la zona invierta en gestión y capacidad
A37: POR QUÉ NO HICIMOS EL FODA CRUZADO
A38: El cruce deriva iniciativas | B38: Cruzar fortalezas y debilidades contra oportunidades y amenazas sirve para derivar iniciativas concretas de acción.
A39: Esta entrega es diagnóstico | B39: El enunciado pide explícitamente no proponer solución todavía: eso va en la sección 6, que se entrega aparte.
A40: La guía de la cátedra tampoco lo hace | B40: Su ejemplo resuelto del caso Distribuidora Montaña presenta un FODA simple, sin cruzar.
A41: Qué sí hicimos | B41: El FODA de arriba, que el enunciado pide cuando habla de oportunidades y amenazas.

Sheet Herramientas
A1: Herramientas de análisis aplicadas
A3: Sección | B3: Herramienta | C3: Autor u origen | D3: Para qué la usamos | E3: Dónde la vimos
A4: 1. La organización | B4: No aplica | D4: Relevamiento descriptivo según la estructura del enunciado | E4: Enunciado del TP
A5: 2. El contexto | B5: Factores del entorno | C5: Adaptado de PESTEL | D5: Tomar las restricciones que pide el enunciado, contando qué le hace cada una a esta empresa | E5: Clase 2 y guía
A6: 2. El contexto | B6: Cinco fuerzas | C6: Porter (1979, 1980) | D6: Analizar el sector: rivalidad, proveedores, compradores, entrantes y sustitutos | E6: Clase 2
A7: 2. El contexto | B7: Cadena de valor | C7: Porter (1985) | D7: Ver dónde se crea y dónde se pierde margen puertas adentro | E7: Clase 2
A8: 2. El contexto | B8: FODA | C8: Planeamiento clásico | D8: Sintetizar lo interno y lo externo en un solo cuadro | E8: Clase 2 y guía
A9: 3. Modelo de negocio | B9: Business Model Canvas | C9: Osterwalder y Pigneur (2010) | D9: Describir cómo la empresa crea, entrega y captura valor hoy | E9: Clase 2
A10: 3. Modelo de negocio | B10: Run / Change the Business | C10: Enfoque bimodal de la materia | D10: Separar lo que sostiene la operación de lo que la transforma | E10: Introductoria y Clase 3
A11: 3. Modelo de negocio | B11: Liderazgo en costos vs. diferenciación | C11: Porter (1980) | D11: Definir la ventaja competitiva real | E11: Clase 2
A12: 4. Propuesta de valor | B12: Value Proposition Canvas | C12: Osterwalder y otros (2014) | D12: Cruzar lo que el cliente necesita con lo que la empresa ofrece | E12: Clase 2
A13: 5. Madurez | B13: Modelo de madurez digital | C13: Cátedra | D13: Evaluar seis dimensiones con escala A a E, más una séptima agregada | E13: Material de cátedra
A14: 5. Madurez | B14: Costo de No Actuar | C14: Fórmula de tres componentes | D14: Poner en plata lo que cuesta no resolver cada brecha | E14: Clase 3
A16: Herramientas que dejamos afuera y por qué
A17: PESTEL completo | B17: Cuatro de sus seis dimensiones volvían vacías en este caso. La guía de la cátedra advierte contra listar factores sin impacto real: usa 'FODA + factores clave', no un PESTEL
A18: FODA cruzado | B18: Su producto son iniciativas y esta entrega es diagnóstico. El FODA simple sí está, que es la forma que usa la guía de la cátedra
A19: Hipótesis de Oportunidad Tecnológica | B19: Es una propuesta de solución (To-Be) y este trabajo es diagnóstico del estado actual
A20: BMC en versión To-Be | B20: El enunciado pide el modelo actual, no el propuesto
A21: Balanced Scorecard y OKR | B21: Corresponden al Hito 3
A22: Design Thinking | B22: Apunta a idear soluciones, que todavía no toca
A23: Plantilla del problema gerencial | B23: Es para la sección 6, que se entrega aparte
